urly/__init__.py
urly/urls.py
urly-0.1.1455780396.dist-info/DESCRIPTION.rst
urly-0.1.1455780396.dist-info/METADATA
urly-0.1.1455780396.dist-info/RECORD
urly-0.1.1455780396.dist-info/WHEEL
urly-0.1.1455780396.dist-info/metadata.json
urly-0.1.1455780396.dist-info/top_level.txt
