Metadata-Version: 2.0
Name: urly
Version: 0.1.1455780396
Summary: Nice URLs for Python
Home-page: UNKNOWN
Author: Robert Lechte
Author-email: robertlechte@gmail.com
License: UNKNOWN
Platform: UNKNOWN
Classifier: Development Status :: 3 - Alpha
Requires-Dist: ipaddress
Requires-Dist: pathlib
Requires-Dist: six
Requires-Dist: werkzeug
